eml_parser/__init__.py
eml_parser/decode.py
eml_parser/parser.py
eml_parser/py.typed
eml_parser/regexes.py
eml_parser/routing.py
eml_parser-2.0.0.dist-info/LICENSE
eml_parser-2.0.0.dist-info/METADATA
eml_parser-2.0.0.dist-info/WHEEL
eml_parser-2.0.0.dist-info/top_level.txt
eml_parser-2.0.0.dist-info/RECORD
