Metadata-Version: 2.1
Name: eml_parser
Version: 2.0.0
Summary: Python EML parser library
Author-email: Georges Toth <georges.toth@govcert.etat.lu>
License: AGPLv3+
Project-URL: Homepage, https://github.com/GOVCERT-LU/eml_parser
Project-URL: Documentation, https://eml-parser.readthedocs.io/
Project-URL: Source, https://github.com/GOVCERT-LU/eml_parser
Project-URL: Tracker, https://github.com/GOVCERT-LU/eml_parser/issues
Project-URL: Changelog, https://github.com/GOVCERT-LU/eml_parser/blob/master/CHANGELOG.md
Keywords: email
Classifier: Development Status :: 5 - Production/Stable
Classifier: License :: OSI Approved :: GNU Affero General Public License v3 or later (AGPLv3+)
Classifier: Intended Audience :: Developers
Classifier: Operating System :: OS Independent
Classifier: Programming Language :: Python :: 3 :: Only
Classifier: Programming Language :: Python :: 3.9
Classifier: Programming Language :: Python :: 3.10
Classifier: Programming Language :: Python :: 3.11
Classifier: Programming Language :: Python :: 3.12
Classifier: Topic :: Communications :: Email
Requires-Python: >=3.9
License-File: LICENSE
Requires-Dist: python-dateutil
Requires-Dist: charset-normalizer
Requires-Dist: publicsuffixlist
Provides-Extra: filemagic
Requires-Dist: file-magic>=0.4.0; extra == "filemagic"
Provides-Extra: regex
Requires-Dist: regex; extra == "regex"
Provides-Extra: docs
Requires-Dist: mkdocs-material; extra == "docs"
Requires-Dist: mkdocstrings[crystal,python]; extra == "docs"
Provides-Extra: dev
Requires-Dist: mypy; extra == "dev"
Requires-Dist: types-python-dateutil; extra == "dev"
Requires-Dist: types-chardet; extra == "dev"
Requires-Dist: ruff; extra == "dev"
Provides-Extra: test
Requires-Dist: pytest; extra == "test"
Requires-Dist: pytest-sugar; extra == "test"
Requires-Dist: coverage; extra == "test"
